mmigrator/__init__.py
mmigrator/cli.py
mmigrator/constants.py
mmigrator/db.py
mmigrator/migration.py
mmigrator/migration_manager.py
mmigrator/process.py
mmigrator/config_manager/__init__.py
mmigrator/config_manager/config_manager.py
mmigrator/config_manager/helpers.py
mmigrator/types/__init__.py
mmigrator-0.2.6.dist-info/METADATA
mmigrator-0.2.6.dist-info/WHEEL
mmigrator-0.2.6.dist-info/entry_points.txt
mmigrator-0.2.6.dist-info/licenses/LICENSE
mmigrator-0.2.6.dist-info/RECORD
