Metadata-Version: 2.3
Name: mmigrator
Version: 0.2.6
Summary: Migration engine for MongoDB
Project-URL: Homepage, https://github.com/sergekovalev/mmigrator
Project-URL: Bug Tracker, https://github.com/sergekovalev/mmigrator/issues
Author-email: Serhii Kovalov <moiserge.k@gmail.com>
License-File: LICENSE
Classifier: License :: OSI Approved :: MIT License
Classifier: Operating System :: OS Independent
Classifier: Programming Language :: Python :: 3
Requires-Python: >=3.0
Requires-Dist: pydantic
Requires-Dist: pymongo
Requires-Dist: snakecase
